doris_mcp_lite/__init__.py
doris_mcp_lite/mcp_app.py
doris_mcp_lite/server.py
doris_mcp_lite/test.py
doris_mcp_lite/config/__init__.py
doris_mcp_lite/config/config.py
doris_mcp_lite/db/__init__.py
doris_mcp_lite/db/db.py
doris_mcp_lite/db/tools.py
doris_mcp_lite/prompts/__init__.py
doris_mcp_lite/prompts/customize_prompts.py
doris_mcp_lite/prompts/general_prompts.py
doris_mcp_lite/res/__init__.py
doris_mcp_lite/res/resources.py
doris_mcp_lite-0.0.3.dist-info/licenses/LICENSE
doris_mcp_lite-0.0.3.dist-info/METADATA
doris_mcp_lite-0.0.3.dist-info/WHEEL
doris_mcp_lite-0.0.3.dist-info/entry_points.txt
doris_mcp_lite-0.0.3.dist-info/top_level.txt
doris_mcp_lite-0.0.3.dist-info/RECORD
