Metadata-Version: 2.4
Name: doris-mcp-lite
Version: 0.0.3
Summary: An MCP server for analytics on Apache Doris database.
Author-email: Hailin Xie <hx101@duke.edu>
Project-URL: Homepage, https://github.com/NomotoK/doris-mcp-lite
Project-URL: Repository, https://github.com/NomotoK/doris-mcp-lite
Requires-Python: >=3.12
License-File: LICENSE
Requires-Dist: dbutils>=3.1.0
Requires-Dist: httpx>=0.28.1
Requires-Dist: mcp[cli]>=1.8.0
Requires-Dist: pandas>=2.2.3
Requires-Dist: pyarrow>=19.0.1
Requires-Dist: pymysql>=1.1.1
Requires-Dist: twine>=6.1.0
Dynamic: license-file
